MANIFEST.in
README.rst
setup.py
src/android/__init__.py
src/android/build.py
src/android/script.py
src/android/tools.py
src/py_androidbuild.egg-info/PKG-INFO
src/py_androidbuild.egg-info/SOURCES.txt
src/py_androidbuild.egg-info/dependency_links.txt
src/py_androidbuild.egg-info/entry_points.txt
src/py_androidbuild.egg-info/top_level.txt