Metadata-Version: 1.0
Name: py-androidbuild
Version: 0.9
Summary: Routines to build Android projects using Python.
Home-page: http://github.com/miracle2k/py-androidbuild/
Author: Michael Elsdörfer
Author-email: michael@elsdoerfer.com
License: BSD
Platform: UNKNOWN
Classifier: Development Status :: 3 - Alpha
Classifier: Intended Audience :: Developers
Classifier: License :: OSI Approved :: Apache Software License
Classifier: Operating System :: OS Independent
Classifier: Programming Language :: Python
Classifier: Topic :: Software Development :: Build Tools
